waxtion/__init__.py
waxtion/cals_coins.py
waxtion/farming.py
waxtion/waxtion.py
waxtion-0.1.9.dist-info/METADATA
waxtion-0.1.9.dist-info/WHEEL
waxtion-0.1.9.dist-info/top_level.txt
waxtion-0.1.9.dist-info/RECORD
